ts_transform/__init__.py
ts_transform/core/__init__.py
ts_transform/core/transformers.py
ts_transform-0.2.2.dist-info/WHEEL
ts_transform-0.2.2.dist-info/METADATA
ts_transform-0.2.2.dist-info/RECORD
